freud_utils/__init__.py
freud_utils/file_dataset.py
freud_utils/json.py
freud_utils/version.py
freud_utils/worker_init.py
Freud_Utils-0.2.dist-info/LICENSE
Freud_Utils-0.2.dist-info/METADATA
Freud_Utils-0.2.dist-info/WHEEL
Freud_Utils-0.2.dist-info/top_level.txt
Freud_Utils-0.2.dist-info/RECORD
