Metadata-Version: 2.1
Name: Freud-Utils
Version: 0.2
Summary: A simplified framework and utilities for PyTorch.
Home-page: https://github.com/freud14/freud-utils
Author: Frédérik Paradis
Author-email: fredy_14@live.fr
License: LGPLv3
Download-URL: https://github.com/freud14/freud-utils/archive/v0.2.zip
Platform: UNKNOWN
Classifier: Development Status :: 3 - Alpha
Classifier: Intended Audience :: Developers
Classifier: Intended Audience :: Education
Classifier: Intended Audience :: Science/Research
Classifier: License :: OSI Approved :: GNU Lesser General Public License v3 (LGPLv3)
Classifier: Programming Language :: Python :: 3
Classifier: Programming Language :: Python :: 3.8
Classifier: Programming Language :: Python :: 3.9
Classifier: Topic :: Software Development :: Libraries
Classifier: Topic :: Software Development :: Libraries :: Python Modules
Requires-Python: >=3.8
Requires-Dist: numpy
Requires-Dist: torch
Requires-Dist: indexed-file
